LICENSE
simsalabim/__init__.py
simsalabim/add_quant_info.py
simsalabim/apl_parser.py
simsalabim/apl_writer.py
simsalabim/convert.py
simsalabim/digest.py
simsalabim/dinosaur_adapter.py
simsalabim/helpers.py
simsalabim/mgf_parser.py
simsalabim/mgf_writer.py
simsalabim/ms2_parser.py
simsalabim/ms2_writer.py
simsalabim/mzml_parser.py
simsalabim/mzml_writer.py
simsalabim/precursor.py
simsalabim/simsalabim.py
simsalabim/spectrum.py
simsalabim/split_apl.py
simsalabim/test/__init__.py
simsalabim/test/test_digest.py
simsalabim/test/test_helpers.py
simsalabim/transform.py
simsalabim-0.2.0.dist-info/LICENSE
simsalabim-0.2.0.dist-info/WHEEL
simsalabim-0.2.0.dist-info/METADATA
simsalabim-0.2.0.dist-info/RECORD
