Metadata-Version: 2.1
Name: simsalabim
Version: 0.2.0
Summary: Simple Interface for MS Applications
Home-page: https://github.com/kusterlab/SIMSI-Transfer
License: Apache-2.0
Keywords: mass spectrometry,proteomics
Author: Matthew The
Author-email: matthew.the@tum.de
Requires-Python: >=3.9,<4.0
Classifier: License :: OSI Approved :: Apache Software License
Classifier: Programming Language :: Python :: 3
Classifier: Programming Language :: Python :: 3.10
Classifier: Programming Language :: Python :: 3.9
Requires-Dist: numpy (>=1.23.1,<2.0.0)
Requires-Dist: psims (>=1.0.1,<2.0.0)
Requires-Dist: pyteomics (>=4.5.3,<5.0.0)
Project-URL: Repository, https://github.com/kusterlab/SIMSI-Transfer
